ytrssil/__init__.py
ytrssil/cli.py
ytrssil/client.py
ytrssil/config.py
ytrssil/main.py
ytrssil/models.py
ytrssil/py.typed
ytrssil-0.8.1.dist-info/METADATA
ytrssil-0.8.1.dist-info/WHEEL
ytrssil-0.8.1.dist-info/entry_points.txt
ytrssil-0.8.1.dist-info/licenses/LICENSE
ytrssil-0.8.1.dist-info/RECORD
