Metadata-Version: 2.4
Name: ytrssil
Version: 0.8.1
Summary: Subscribe to YouTube RSS feeds and keep track of watched videos
Project-URL: Homepage, https://github.com/TheEdgeOfRage/ytrssil/cli
Author-email: Pavle Portic <git@theedgeofrage.com>
License-Expression: BSD-3-Clause
License-File: LICENSE
Classifier: License :: OSI Approved :: BSD License
Classifier: Operating System :: POSIX :: Linux
Classifier: Programming Language :: Python :: 3
Classifier: Programming Language :: Python :: 3 :: Only
Classifier: Programming Language :: Python :: 3.12
Classifier: Programming Language :: Python :: 3.13
Requires-Python: >=3.12
